mkdocs_panzoom_plugin/__init__.py
mkdocs_panzoom_plugin/exclude.py
mkdocs_panzoom_plugin/html_page.py
mkdocs_panzoom_plugin/markdown_extension.py
mkdocs_panzoom_plugin/panzoom_box.py
mkdocs_panzoom_plugin/plugin.py
mkdocs_panzoom_plugin/custom/panzoom.css
mkdocs_panzoom_plugin/custom/zoompan.js
mkdocs_panzoom_plugin/panzoom/LICENCE
mkdocs_panzoom_plugin/panzoom/panzoom.min.js
mkdocs_panzoom_plugin-0.5.2.dist-info/licenses/LICENSE
mkdocs_panzoom_plugin-0.5.2.dist-info/METADATA
mkdocs_panzoom_plugin-0.5.2.dist-info/WHEEL
mkdocs_panzoom_plugin-0.5.2.dist-info/entry_points.txt
mkdocs_panzoom_plugin-0.5.2.dist-info/top_level.txt
mkdocs_panzoom_plugin-0.5.2.dist-info/RECORD
