Metadata-Version: 2.4
Name: mkdocs-panzoom-plugin
Version: 0.5.2
Summary: MkDocs Plugin to enable pan & zoom on images and mermaid diagrams
Home-page: https://github.com/PLAYG0N/mkdocs-panzoom.git
Author: PLAYG0N
Author-email: playg0nofficial@gmail.com
License: MIT
Keywords: mkdocs zoom pan plugin mermaid images
Classifier: Intended Audience :: Developers
Classifier: Intended Audience :: Information Technology
Classifier: License :: OSI Approved :: MIT License
Classifier: Programming Language :: Python
Classifier: Programming Language :: Python :: 3 :: Only
Classifier: Programming Language :: Python :: 3.8
Classifier: Programming Language :: Python :: 3.9
Classifier: Programming Language :: Python :: 3.10
Classifier: Programming Language :: Python :: 3.11
Requires-Python: >=3.7
License-File: LICENSE
Requires-Dist: mkdocs>=1.0.4
Dynamic: author
Dynamic: author-email
Dynamic: classifier
Dynamic: description
Dynamic: description-content-type
Dynamic: home-page
Dynamic: keywords
Dynamic: license
Dynamic: license-file
Dynamic: requires-dist
Dynamic: requires-python
Dynamic: summary
